{
  "{page_lang}" : "zh_cn",
  "{page_title}" : "香港阳光光电有限公司",
  "{page_description}" : "官方网站",
  "{page_keywords}" : "香港阳光",
  "{menu_home}" : "首页",
  "{menu_solution}" : "解决方案",
  "{menu_product}" : "产品",
  "{menu_about}" : "关于公司",
  "{menu_contact}" : "联系我们",
  "{selling_product_tip}" : "热销产品",
  "{more_tip}" : "更多...",
  "{need_help_tip}" : "需要帮助吗？请",
  "{contact_us_tip}" : "联系我们",
  "{copyright_tip}" : "香港阳光光电有限公司 版权所有",
  "{page_footer}" : "深圳某某地址 电话：0001 传真：0001 email：11@126.com",
  "{search-product-tip}" : "产品搜索",
  "{search-select-product-type-tip}" : "选择系列",
  "{search-select-product-name-tip}" : "选择产品",
  "{search-select-product-key-words}" : "请输入关键字",
  "{contact_description_info}" : "我们是致力于生产。大打99及解决我们是致力于生产。大打99及解决我们是致力于生产。大打99及解决我们是致力于生产。大打99及解决",
  "{contact_building_tip}" : "SunShine HQ",
  "{contact_building_info}" : "12-D (CCA), Phase 5D.H.A.<br/> Lahore Pakistan<br/>Tel: +92.42.37060558",
  "{contact_building_btn}" : "联系我们",
  "{contact_support_tip}" : "We're here to help 24/7",
  "{contact_support_info}" : "Got a question about using Fishry?<br/>The Fishry support team is available 24 hours a day, 7 days a week, by email.",
  "{contact_support_btn}" : "联系我们",
  "{contact_modal_title}" : "联系我们",
  "{contact_modal_ok_btn}" : "确定",
  "{contact_modal_cancel_btn}" : "取消",
  "{contact-success-tip}" : "提交成功！",
  "{contact-fail-tip}" : "提交失败！",
  "{contact-form-name}" : "您的姓名",
  "{contact-form-email}" : "电子邮箱",
  "{contact-form-tel}" : "手机号码",
  "{contact-form-subject}" : "主题",
  "{contact-form-content}" : "内容",
  "{email-error-tip}" : "电子邮箱格式不对！"
}